{
    "exporter_port": 8000,
    "rpc_collector" : {
        "refresh_interval_seconds": 10
    },
    "price_collector": {
        "enable": true,
        "refresh_interval_seconds": 10
    },
    "notifications": {
        "enable": true,
        "refresh_interval_seconds": 10,
        "status_interval_minutes": 60,
        "lost_plots_alert_threshold": 1,
        "disable_proof_found_alert": false,
        "status_service_url": "tgram://{bot_token}/{chat_id}/",
        "alert_service_url": "tgram://{bot_token}/{chat_id}/"
    }
}